{
  "task": "P1-2.2c commit->tick->module-as-source 触发链修复",
  "date": "2026-03-19",
  "branch": "agent/v4-perf-p1-2-2c-module-source-tick",
  "status": "green",
  "redlines": {
    "StateTrait.ExternalStoreTrait.Runtime.test.ts::perf skeleton timeout": "passed",
    "ModuleAsSource.tick.test.ts::target state and tick assertions": "passed"
  },
  "commands": [
    {
      "cmd": "pnpm -C packages/logix-core exec vitest run test/internal/StateTrait/StateTrait.ExternalStoreTrait.Runtime.test.ts test/internal/Runtime/ModuleAsSource.tick.test.ts",
      "returncode": 0,
      "tests": {
        "filesPassed": 2,
        "testsPassed": 14
      }
    },
    {
      "cmd": "pnpm -C packages/logix-core exec vitest run test/internal/Bound/BoundApiRuntime.stateUpdateWholeStateFallback.Perf.off.test.ts",
      "returncode": 0,
      "tests": {
        "filesPassed": 1,
        "testsPassed": 1
      }
    }
  ],
  "samples": {
    "perfExternalStoreIngestProxy": {
      "tickDelta": 1,
      "finalValues": [
        100,
        101,
        102,
        103
      ]
    }
  }
}
